PythonMETAR/__init__.py
PythonMETAR/metar.py
PythonMETAR/test.py
PythonMETAR-1.0.0.1.dist-info/LICENSE
PythonMETAR-1.0.0.1.dist-info/METADATA
PythonMETAR-1.0.0.1.dist-info/WHEEL
PythonMETAR-1.0.0.1.dist-info/top_level.txt
PythonMETAR-1.0.0.1.dist-info/RECORD
