Metadata-Version: 2.1
Name: PythonMETAR
Version: 1.0.0.1
Summary: METAR Python Library
Home-page: https://github.com/MatthieuBOUCHET/PythonMETAR
Author: Matthieu BOUCHET
Author-email: matthieu.bouchet@outlook.com
License: UNKNOWN
Platform: UNKNOWN
Classifier: Development Status :: 4 - Beta
Classifier: Programming Language :: Python :: 3
Classifier: License :: OSI Approved :: MIT License
Classifier: Operating System :: OS Independent
Requires-Python: >=3
